{"assets":{"80336EAB6D3062A19986B2D664A98CCB":{"type":"texture","index":48,"assetRequest":{"type":"slide","state":"object","slide":"C081CBF7-4D93-4160-A948-0256FBB752D3"},"url":{"web":"assets/80336EAB6D3062A19986B2D664A98CCB.svg"},"width":260,"height":167},"2F547A1FDD8A87CF921B459FBDFA3AB3":{"type":"texture","index":47,"assetRequest":{"type":"slide","state":"object","slide":"C081CBF7-4D93-4160-A948-0256FBB752D3"},"url":{"web":"assets/2F547A1FDD8A87CF921B459FBDFA3AB3.svg"},"width":484,"height":704},"9A26649A2F9F2AB8B9FE1A2628DE396B":{"type":"texture","index":51,"assetRequest":{"type":"slide","state":"object","slide":"C081CBF7-4D93-4160-A948-0256FBB752D3"},"url":{"web":"assets/9A26649A2F9F2AB8B9FE1A2628DE396B.svg"},"width":1738,"height":722},"01B3871BA9FB8840BDC92BFC758C8D4E":{"type":"texture","index":50,"assetRequest":{"type":"slide","state":"object","slide":"C081CBF7-4D93-4160-A948-0256FBB752D3"},"url":{"web":"assets/01B3871BA9FB8840BDC92BFC758C8D4E.svg"},"width":797,"height":676},"08F2739282076EE2A5583663EA27282C":{"type":"texture","index":52,"assetRequest":{"type":"slide","state":"object","slide":"C081CBF7-4D93-4160-A948-0256FBB752D3"},"url":{"web":"assets/08F2739282076EE2A5583663EA27282C.svg"},"width":358,"height":182},"93554756A441045606ED88672D8E8293":{"type":"texture","index":46,"assetRequest":{"type":"slide","state":"object","slide":"C081CBF7-4D93-4160-A948-0256FBB752D3"},"url":{"web":"assets/93554756A441045606ED88672D8E8293.svg"},"width":1798,"height":455},"37531B31BC3BB14BFC320A157738694F":{"type":"texture","index":45,"assetRequest":{"type":"slide","state":"object","slide":"C081CBF7-4D93-4160-A948-0256FBB752D3"},"url":{"web":"assets/37531B31BC3BB14BFC320A157738694F.svg"},"width":1538,"height":728},"7FD96FD65160E41977E3C562FFAC604F":{"type":"texture","index":44,"assetRequest":{"type":"slide","state":"background","slide":"C081CBF7-4D93-4160-A948-0256FBB752D3"},"url":{"web":"assets/7FD96FD65160E41977E3C562FFAC604F.svg"},"width":1280,"height":720},"13FC1D004785409A6DD9A4F21AF9CCC1":{"type":"texture","index":49,"assetRequest":{"type":"slide","state":"object","slide":"C081CBF7-4D93-4160-A948-0256FBB752D3"},"url":{"web":"assets/13FC1D004785409A6DD9A4F21AF9CCC1.svg"},"width":1377,"height":723}},"events":[{"effects":[{"beginTime":0,"baseLayer":{"animations":[],"initialState":{"affineTransform":[1,0,0,1,0,0],"masksToBounds":false,"rotation":0,"scale":1,"position":{"pointX":640,"pointY":360},"width":1280,"sublayerTransform":[1,0,0,0,0,1,0,0,0,0,1,0,0,0,0,1],"contentsRect":{"y":0,"x":0,"width":1,"height":1},"opacity":1,"edgeAntialiasingMask":251658240,"height":720,"hidden":false,"anchorPoint":{"pointX":0.5,"pointY":0.5}},"objectID":"0","layers":[{"animations":[],"initialState":{"affineTransform":[1,0,0,1,0,0],"masksToBounds":false,"rotation":0,"scale":1,"position":{"pointX":640,"pointY":360},"width":1280,"sublayerTransform":[1,0,0,0,0,1,0,0,0,0,1,-0.0005251186870016398,0,0,0,1],"contentsRect":{"y":0,"x":0,"width":1,"height":1},"opacity":1,"edgeAntialiasingMask":251658240,"height":720,"hidden":false,"anchorPoint":{"pointX":0.5,"pointY":0.5}},"layers":[{"animations":[{"timeOffset":0,"beginTime":0,"repeatCount":0,"animations":[{"timeOffset":0,"from":{"scalar":0},"beginTime":0,"repeatCount":0,"fillMode":"both","duration":0.800000011920929,"autoreverses":false,"timingFunction":"Linear","property":"zPosition","to":{"scalar":0}}],"fillMode":"both","autoreverses":false,"duration":0.800000011920929}],"initialState":{"affineTransform":[1,0,0,1,0,0],"masksToBounds":false,"rotation":0,"scale":1,"position":{"pointX":640,"pointY":360},"width":1280,"sublayerTransform":[1,0,0,0,0,1,0,0,0,0,1,0,0,0,0,1],"contentsRect":{"y":0,"x":0,"width":1,"height":1},"opacity":1,"edgeAntialiasingMask":251658240,"height":720,"hidden":false,"anchorPoint":{"pointX":0.5,"pointY":0.5}},"layers":[{"animations":[],"layers":[],"initialState":{"affineTransform":[1,0,0,1,0,0],"masksToBounds":false,"rotation":0,"scale":1,"position":{"pointX":640,"pointY":360},"width":1280,"sublayerTransform":[1,0,0,0,0,1,0,0,0,0,1,0,0,0,0,1],"contentsRect":{"y":0,"x":0,"width":1,"height":1},"opacity":1,"edgeAntialiasingMask":0,"height":720,"hidden":false,"anchorPoint":{"pointX":0.5,"pointY":0.5}},"texture":"7FD96FD65160E41977E3C562FFAC604F"}]}]},{"animations":[{"timeOffset":0,"beginTime":0,"repeatCount":0,"animations":[{"timeOffset":0,"from":{"scalar":0.001},"beginTime":0,"repeatCount":0,"fillMode":"both","duration":0.800000011920929,"autoreverses":false,"timingFunction":"Linear","property":"zPosition","to":{"scalar":0.001}}],"fillMode":"both","autoreverses":false,"duration":0.800000011920929}],"initialState":{"affineTransform":[1,0,0,1,0,0],"masksToBounds":false,"rotation":0,"scale":1,"position":{"pointX":768,"pointY":360},"width":1535.686279296875,"sublayerTransform":[1,0,0,0,0,1,0,0,0,0,1,0,0,0,0,1],"contentsRect":{"y":0,"x":0,"width":1,"height":1},"opacity":1,"edgeAntialiasingMask":251658240,"height":724.095703125,"hidden":false,"anchorPoint":{"pointX":0.5,"pointY":0.5}},"layers":[{"animations":[{"timeOffset":0,"beginTime":0,"repeatCount":0,"animations":[{"timeOffset":0,"from":{"scalar":1},"beginTime":0,"repeatCount":0,"fillMode":"forwards","duration":0.800000011920929,"autoreverses":false,"timingFunction":"Linear","property":"opacity","to":{"scalar":0}},{"timeOffset":0,"from":{"scalar":true},"beginTime":0.799200011909008,"repeatCount":0,"fillMode":"forwards","property":"hidden","autoreverses":false,"duration":0.0008000000119209316,"to":{"scalar":true}}],"fillMode":"both","autoreverses":false,"duration":0.800000011920929}],"layers":[],"initialState":{"affineTransform":[1,0,0,1,0,0],"masksToBounds":false,"rotation":0,"scale":1,"position":{"pointX":767.8431396484375,"pointY":362.0478515625},"width":1538,"sublayerTransform":[1,0,0,0,0,1,0,0,0,0,1,0,0,0,0,1],"contentsRect":{"y":0,"x":0,"width":1,"height":1},"opacity":1,"edgeAntialiasingMask":0,"height":728,"hidden":false,"anchorPoint":{"pointX":0.5,"pointY":0.5}},"texture":"37531B31BC3BB14BFC320A157738694F"}]},{"animations":[{"timeOffset":0,"beginTime":0,"repeatCount":0,"animations":[{"timeOffset":0,"from":{"scalar":0.002},"beginTime":0,"repeatCount":0,"fillMode":"both","duration":0.800000011920929,"autoreverses":false,"timingFunction":"Linear","property":"zPosition","to":{"scalar":0.002}}],"fillMode":"both","autoreverses":false,"duration":0.800000011920929}],"initialState":{"affineTransform":[1,0,0,1,0,0],"masksToBounds":false,"rotation":0,"scale":1,"position":{"pointX":897.4190877303481,"pointY":224.5717718601227},"width":1795.086547851562,"sublayerTransform":[1,0,0,0,0,1,0,0,0,0,1,0,0,0,0,1],"contentsRect":{"y":0,"x":0,"width":1,"height":1},"opacity":1,"edgeAntialiasingMask":251658240,"height":452.06103515625,"hidden":false,"anchorPoint":{"pointX":0.5,"pointY":0.5}},"layers":[{"animations":[{"timeOffset":0,"beginTime":0,"repeatCount":0,"animations":[{"timeOffset":0,"from":{"scalar":1},"beginTime":0,"repeatCount":0,"fillMode":"forwards","duration":0.800000011920929,"autoreverses":false,"timingFunction":"Linear","property":"opacity","to":{"scalar":0}},{"timeOffset":0,"from":{"scalar":true},"beginTime":0.799200011909008,"repeatCount":0,"fillMode":"forwards","property":"hidden","autoreverses":false,"duration":0.0008000000119209316,"to":{"scalar":true}}],"fillMode":"both","autoreverses":false,"duration":0.800000011920929}],"layers":[],"initialState":{"affineTransform":[1,0,0,1,0,0],"masksToBounds":false,"rotation":0,"scale":1,"position":{"pointX":897.5432739257814,"pointY":226.030517578125},"width":1798,"sublayerTransform":[1,0,0,0,0,1,0,0,0,0,1,0,0,0,0,1],"contentsRect":{"y":0,"x":0,"width":1,"height":1},"opacity":1,"edgeAntialiasingMask":0,"height":455,"hidden":false,"anchorPoint":{"pointX":0.5002330855007499,"pointY":0.500157740351918}},"texture":"93554756A441045606ED88672D8E8293"}]},{"animations":[{"timeOffset":0,"beginTime":0,"repeatCount":0,"animations":[{"timeOffset":0,"from":{"scalar":0.003},"beginTime":0,"repeatCount":0,"fillMode":"both","duration":0.800000011920929,"autoreverses":false,"timingFunction":"Linear","property":"zPosition","to":{"scalar":0.003}}],"fillMode":"both","autoreverses":false,"duration":0.800000011920929}],"initialState":{"affineTransform":[1,0,0,1,0,0],"masksToBounds":false,"rotation":0,"scale":1,"position":{"pointX":909.3333129882812,"pointY":369.3333339691162},"width":481,"sublayerTransform":[1,0,0,0,0,1,0,0,0,0,1,0,0,0,0,1],"contentsRect":{"y":0,"x":0,"width":1,"height":1},"opacity":1,"edgeAntialiasingMask":251658240,"height":701,"hidden":false,"anchorPoint":{"pointX":0.5,"pointY":0.5}},"layers":[{"animations":[{"timeOffset":0,"beginTime":0,"repeatCount":0,"animations":[{"timeOffset":0,"from":{"scalar":1},"beginTime":0,"repeatCount":0,"fillMode":"forwards","duration":0.800000011920929,"autoreverses":false,"timingFunction":"Linear","property":"opacity","to":{"scalar":0}},{"timeOffset":0,"from":{"scalar":true},"beginTime":0.799200011909008,"repeatCount":0,"fillMode":"forwards","property":"hidden","autoreverses":false,"duration":0.0008000000119209316,"to":{"scalar":true}}],"fillMode":"both","autoreverses":false,"duration":0.800000011920929}],"layers":[],"initialState":{"affineTransform":[1,0,0,1,0,0],"masksToBounds":false,"rotation":0,"scale":1,"position":{"pointX":240.5,"pointY":350.5},"width":484,"sublayerTransform":[1,0,0,0,0,1,0,0,0,0,1,0,0,0,0,1],"contentsRect":{"y":0,"x":0,"width":1,"height":1},"opacity":1,"edgeAntialiasingMask":0,"height":704,"hidden":false,"anchorPoint":{"pointX":0.5006886631989281,"pointY":0.5004734857515856}},"texture":"2F547A1FDD8A87CF921B459FBDFA3AB3"}]},{"animations":[{"timeOffset":0,"beginTime":0,"repeatCount":0,"animations":[{"timeOffset":0,"from":{"scalar":0.004},"beginTime":0,"repeatCount":0,"fillMode":"both","duration":0.800000011920929,"autoreverses":false,"timingFunction":"Linear","property":"zPosition","to":{"scalar":0.004}}],"fillMode":"both","autoreverses":false,"duration":0.800000011920929}],"initialState":{"affineTransform":[1,0,0,1,0,0],"masksToBounds":false,"rotation":0,"scale":1,"position":{"pointX":194.6666641235352,"pointY":597.3333129882812},"width":257,"sublayerTransform":[1,0,0,0,0,1,0,0,0,0,1,0,0,0,0,1],"contentsRect":{"y":0,"x":0,"width":1,"height":1},"opacity":1,"edgeAntialiasingMask":251658240,"height":164,"hidden":false,"anchorPoint":{"pointX":0.5,"pointY":0.5}},"layers":[{"animations":[{"timeOffset":0,"beginTime":0,"repeatCount":0,"animations":[{"timeOffset":0,"from":{"scalar":1},"beginTime":0,"repeatCount":0,"fillMode":"forwards","duration":0.800000011920929,"autoreverses":false,"timingFunction":"Linear","property":"opacity","to":{"scalar":0}},{"timeOffset":0,"from":{"scalar":true},"beginTime":0.799200011909008,"repeatCount":0,"fillMode":"forwards","property":"hidden","autoreverses":false,"duration":0.0008000000119209316,"to":{"scalar":true}}],"fillMode":"both","autoreverses":false,"duration":0.800000011920929}],"layers":[],"initialState":{"affineTransform":[1,0,0,1,0,0],"masksToBounds":false,"rotation":0,"scale":1,"position":{"pointX":128.5,"pointY":82},"width":260,"sublayerTransform":[1,0,0,0,0,1,0,0,0,0,1,0,0,0,0,1],"contentsRect":{"y":0,"x":0,"width":1,"height":1},"opacity":1,"edgeAntialiasingMask":0,"height":167,"hidden":false,"anchorPoint":{"pointX":0.4987179389366737,"pointY":0.4990018741813249}},"texture":"80336EAB6D3062A19986B2D664A98CCB"}]},{"animations":[{"timeOffset":0,"beginTime":0,"repeatCount":0,"animations":[{"timeOffset":0,"from":{"scalar":0.005},"beginTime":0,"repeatCount":0,"fillMode":"both","duration":0.800000011920929,"autoreverses":false,"timingFunction":"Linear","property":"zPosition","to":{"scalar":0.005}}],"fillMode":"both","autoreverses":false,"duration":0.800000011920929}],"initialState":{"affineTransform":[1,0,0,1,0,0],"masksToBounds":false,"rotation":0,"scale":1,"position":{"pointX":597.3333358764648,"pointY":359.9999999999999},"width":1373,"sublayerTransform":[1,0,0,0,0,1,0,0,0,0,1,0,0,0,0,1],"contentsRect":{"y":0,"x":0,"width":1,"height":1},"opacity":1,"edgeAntialiasingMask":251658240,"height":720,"hidden":false,"anchorPoint":{"pointX":0.5,"pointY":0.5}},"layers":[{"animations":[{"timeOffset":0,"beginTime":0,"repeatCount":0,"animations":[{"timeOffset":0,"from":{"scalar":0},"beginTime":0,"repeatCount":0,"fillMode":"both","duration":0.800000011920929,"autoreverses":false,"timingFunction":"Linear","property":"opacity","to":{"scalar":1}},{"timeOffset":0,"from":{"scalar":false},"beginTime":0,"repeatCount":0,"fillMode":"forwards","property":"hidden","autoreverses":false,"duration":0.800000011920929,"to":{"scalar":false}}],"fillMode":"both","autoreverses":false,"duration":0.800000011920929}],"layers":[],"initialState":{"affineTransform":[1,0,0,1,0,0],"masksToBounds":false,"rotation":0,"scale":1,"position":{"pointX":686.4999999999999,"pointY":360},"width":1377,"sublayerTransform":[1,0,0,0,0,1,0,0,0,0,1,0,0,0,0,1],"contentsRect":{"y":0,"x":0,"width":1,"height":1},"opacity":1,"edgeAntialiasingMask":0,"height":723,"hidden":true,"anchorPoint":{"pointX":0.5006051821906062,"pointY":0.5006915629322267}},"texture":"13FC1D004785409A6DD9A4F21AF9CCC1"}]},{"animations":[{"timeOffset":0,"beginTime":0,"repeatCount":0,"animations":[{"timeOffset":0,"from":{"scalar":0.006},"beginTime":0,"repeatCount":0,"fillMode":"both","duration":0.800000011920929,"autoreverses":false,"timingFunction":"Linear","property":"zPosition","to":{"scalar":0.006}}],"fillMode":"both","autoreverses":false,"duration":0.800000011920929}],"initialState":{"affineTransform":[1,0,0,1,0,0],"masksToBounds":false,"rotation":0,"scale":1,"position":{"pointX":703.3333435058594,"pointY":383.3333320617676},"width":793,"sublayerTransform":[1,0,0,0,0,1,0,0,0,0,1,0,0,0,0,1],"contentsRect":{"y":0,"x":0,"width":1,"height":1},"opacity":1,"edgeAntialiasingMask":251658240,"height":673,"hidden":false,"anchorPoint":{"pointX":0.5,"pointY":0.5}},"layers":[{"animations":[{"timeOffset":0,"beginTime":0,"repeatCount":0,"animations":[{"timeOffset":0,"from":{"scalar":0},"beginTime":0,"repeatCount":0,"fillMode":"both","duration":0.800000011920929,"autoreverses":false,"timingFunction":"Linear","property":"opacity","to":{"scalar":1}},{"timeOffset":0,"from":{"scalar":false},"beginTime":0,"repeatCount":0,"fillMode":"forwards","property":"hidden","autoreverses":false,"duration":0.800000011920929,"to":{"scalar":false}}],"fillMode":"both","autoreverses":false,"duration":0.800000011920929}],"layers":[],"initialState":{"affineTransform":[1,0,0,1,0,0],"masksToBounds":false,"rotation":0,"scale":1,"position":{"pointX":396.5,"pointY":336.5},"width":797,"sublayerTransform":[1,0,0,0,0,1,0,0,0,0,1,0,0,0,0,1],"contentsRect":{"y":0,"x":0,"width":1,"height":1},"opacity":1,"edgeAntialiasingMask":0,"height":676,"hidden":true,"anchorPoint":{"pointX":0.5010456003837633,"pointY":0.5004930947659284}},"texture":"01B3871BA9FB8840BDC92BFC758C8D4E"}]},{"animations":[{"timeOffset":0,"beginTime":0,"repeatCount":0,"animations":[{"timeOffset":0,"from":{"scalar":0.007},"beginTime":0,"repeatCount":0,"fillMode":"both","duration":0.800000011920929,"autoreverses":false,"timingFunction":"Linear","property":"zPosition","to":{"scalar":0.007}}],"fillMode":"both","autoreverses":false,"duration":0.800000011920929}],"initialState":{"affineTransform":[1,0,0,1,0,0],"masksToBounds":false,"rotation":0,"scale":1,"position":{"pointX":414.6666564941406,"pointY":360},"width":1735,"sublayerTransform":[1,0,0,0,0,1,0,0,0,0,1,0,0,0,0,1],"contentsRect":{"y":0,"x":0,"width":1,"height":1},"opacity":1,"edgeAntialiasingMask":251658240,"height":720,"hidden":false,"anchorPoint":{"pointX":0.5,"pointY":0.5}},"layers":[{"animations":[{"timeOffset":0,"beginTime":0,"repeatCount":0,"animations":[{"timeOffset":0,"from":{"scalar":0},"beginTime":0,"repeatCount":0,"fillMode":"both","duration":0.800000011920929,"autoreverses":false,"timingFunction":"Linear","property":"opacity","to":{"scalar":1}},{"timeOffset":0,"from":{"scalar":false},"beginTime":0,"repeatCount":0,"fillMode":"forwards","property":"hidden","autoreverses":false,"duration":0.800000011920929,"to":{"scalar":false}}],"fillMode":"both","autoreverses":false,"duration":0.800000011920929}],"layers":[],"initialState":{"affineTransform":[1,0,0,1,0,0],"masksToBounds":false,"rotation":0,"scale":1,"position":{"pointX":867.5,"pointY":360},"width":1738,"sublayerTransform":[1,0,0,0,0,1,0,0,0,0,1,0,0,0,0,1],"contentsRect":{"y":0,"x":0,"width":1,"height":1},"opacity":1,"edgeAntialiasingMask":0,"height":722,"hidden":true,"anchorPoint":{"pointX":0.4998082028159612,"pointY":0.5}},"texture":"9A26649A2F9F2AB8B9FE1A2628DE396B"}]},{"animations":[{"timeOffset":0,"beginTime":0,"repeatCount":0,"animations":[{"timeOffset":0,"from":{"scalar":0.008},"beginTime":0,"repeatCount":0,"fillMode":"both","duration":0.800000011920929,"autoreverses":false,"timingFunction":"Linear","property":"zPosition","to":{"scalar":0.008}}],"fillMode":"both","autoreverses":false,"duration":0.800000011920929}],"initialState":{"affineTransform":[1,0,0,1,0,0],"masksToBounds":false,"rotation":0,"scale":1,"position":{"pointX":233.3333320617676,"pointY":584},"width":355,"sublayerTransform":[1,0,0,0,0,1,0,0,0,0,1,0,0,0,0,1],"contentsRect":{"y":0,"x":0,"width":1,"height":1},"opacity":1,"edgeAntialiasingMask":251658240,"height":180,"hidden":false,"anchorPoint":{"pointX":0.5,"pointY":0.5}},"layers":[{"animations":[{"timeOffset":0,"beginTime":0,"repeatCount":0,"animations":[{"timeOffset":0,"from":{"scalar":0},"beginTime":0,"repeatCount":0,"fillMode":"both","duration":0.800000011920929,"autoreverses":false,"timingFunction":"Linear","property":"opacity","to":{"scalar":1}},{"timeOffset":0,"from":{"scalar":false},"beginTime":0,"repeatCount":0,"fillMode":"forwards","property":"hidden","autoreverses":false,"duration":0.800000011920929,"to":{"scalar":false}}],"fillMode":"both","autoreverses":false,"duration":0.800000011920929}],"layers":[],"initialState":{"affineTransform":[1,0,0,1,0,0],"masksToBounds":false,"rotation":0,"scale":1,"position":{"pointX":177.5,"pointY":90},"width":358,"sublayerTransform":[1,0,0,0,0,1,0,0,0,0,1,0,0,0,0,1],"contentsRect":{"y":0,"x":0,"width":1,"height":1},"opacity":1,"edgeAntialiasingMask":0,"height":182,"hidden":true,"anchorPoint":{"pointX":0.5009310951446022,"pointY":0.5}},"texture":"08F2739282076EE2A5583663EA27282C"}]}]},"effects":[],"duration":0.800000011920929,"type":"transition","name":"apple:magic-move-implied-motion-path","objectID":"0"}],"automaticPlay":true,"hyperlinks":[],"accessibility":[{"text":"pasted-image.tif","targetRectangle":{"y":-2.0478515625,"x":0.1568603515625,"width":1535.686279296875,"height":724.095703125}},{"text":"pasted-image.tif","targetRectangle":{"y":515.3333129882812,"x":66.16666412353516,"width":257,"height":164}},{"text":"pasted-image.tif","targetRectangle":{"y":18.83333396911621,"x":668.8333129882812,"width":481,"height":701}},{"text":"pasted-image.tif","targetRectangle":{"y":-1.458745718002319,"x":-0.1241861954331398,"width":1795.086547851562,"height":452.06103515625}}],"baseLayer":{"animations":[],"initialState":{"affineTransform":[1,0,0,1,0,0],"masksToBounds":false,"rotation":0,"scale":1,"position":{"pointX":640,"pointY":360},"width":1280,"sublayerTransform":[1,0,0,0,0,1,0,0,0,0,1,0,0,0,0,1],"contentsRect":{"y":0,"x":0,"width":1,"height":1},"opacity":1,"edgeAntialiasingMask":251658240,"height":720,"hidden":false,"anchorPoint":{"pointX":0.5,"pointY":0.5}},"objectID":"0","layers":[{"animations":[],"initialState":{"affineTransform":[1,0,0,1,0,0],"masksToBounds":false,"rotation":0,"scale":1,"position":{"pointX":640,"pointY":360},"width":1280,"sublayerTransform":[1,0,0,0,0,1,0,0,0,0,1,-0.0005251186870016398,0,0,0,1],"contentsRect":{"y":0,"x":0,"width":1,"height":1},"opacity":1,"edgeAntialiasingMask":251658240,"height":720,"hidden":false,"anchorPoint":{"pointX":0.5,"pointY":0.5}},"layers":[{"animations":[],"initialState":{"affineTransform":[1,0,0,1,0,0],"masksToBounds":false,"rotation":0,"scale":1,"position":{"pointX":640,"pointY":360},"width":1280,"sublayerTransform":[1,0,0,0,0,1,0,0,0,0,1,0,0,0,0,1],"contentsRect":{"y":0,"x":0,"width":1,"height":1},"opacity":1,"edgeAntialiasingMask":251658240,"height":720,"hidden":false,"anchorPoint":{"pointX":0.5,"pointY":0.5}},"layers":[{"animations":[],"layers":[],"initialState":{"affineTransform":[1,0,0,1,0,0],"masksToBounds":false,"rotation":0,"scale":1,"position":{"pointX":640,"pointY":360},"width":1280,"sublayerTransform":[1,0,0,0,0,1,0,0,0,0,1,0,0,0,0,1],"contentsRect":{"y":0,"x":0,"width":1,"height":1},"opacity":1,"edgeAntialiasingMask":0,"height":720,"hidden":false,"anchorPoint":{"pointX":0.5,"pointY":0.5}},"texture":"7FD96FD65160E41977E3C562FFAC604F"}]}]},{"animations":[],"initialState":{"affineTransform":[1,0,0,1,0,0],"masksToBounds":false,"rotation":0,"scale":1,"position":{"pointX":768,"pointY":360},"width":1535.686279296875,"sublayerTransform":[1,0,0,0,0,1,0,0,0,0,1,0,0,0,0,1],"contentsRect":{"y":0,"x":0,"width":1,"height":1},"opacity":1,"edgeAntialiasingMask":251658240,"height":724.095703125,"hidden":false,"anchorPoint":{"pointX":0.5,"pointY":0.5}},"layers":[{"animations":[],"layers":[],"initialState":{"affineTransform":[1,0,0,1,0,0],"masksToBounds":false,"rotation":0,"scale":1,"position":{"pointX":767.8431396484375,"pointY":362.0478515625},"width":1538,"sublayerTransform":[1,0,0,0,0,1,0,0,0,0,1,0,0,0,0,1],"contentsRect":{"y":0,"x":0,"width":1,"height":1},"opacity":1,"edgeAntialiasingMask":0,"height":728,"hidden":false,"anchorPoint":{"pointX":0.5,"pointY":0.5}},"texture":"37531B31BC3BB14BFC320A157738694F"}]},{"animations":[],"initialState":{"affineTransform":[1,0,0,1,0,0],"masksToBounds":false,"rotation":0,"scale":1,"position":{"pointX":897.4190877303481,"pointY":224.5717718601227},"width":1795.086547851562,"sublayerTransform":[1,0,0,0,0,1,0,0,0,0,1,0,0,0,0,1],"contentsRect":{"y":0,"x":0,"width":1,"height":1},"opacity":1,"edgeAntialiasingMask":251658240,"height":452.06103515625,"hidden":false,"anchorPoint":{"pointX":0.5,"pointY":0.5}},"layers":[{"animations":[],"layers":[],"initialState":{"affineTransform":[1,0,0,1,0,0],"masksToBounds":false,"rotation":0,"scale":1,"position":{"pointX":897.5432739257814,"pointY":226.030517578125},"width":1798,"sublayerTransform":[1,0,0,0,0,1,0,0,0,0,1,0,0,0,0,1],"contentsRect":{"y":0,"x":0,"width":1,"height":1},"opacity":1,"edgeAntialiasingMask":0,"height":455,"hidden":false,"anchorPoint":{"pointX":0.5002330855007499,"pointY":0.500157740351918}},"texture":"93554756A441045606ED88672D8E8293"}]},{"animations":[],"initialState":{"affineTransform":[1,0,0,1,0,0],"masksToBounds":false,"rotation":0,"scale":1,"position":{"pointX":909.3333129882812,"pointY":369.3333339691162},"width":481,"sublayerTransform":[1,0,0,0,0,1,0,0,0,0,1,0,0,0,0,1],"contentsRect":{"y":0,"x":0,"width":1,"height":1},"opacity":1,"edgeAntialiasingMask":251658240,"height":701,"hidden":false,"anchorPoint":{"pointX":0.5,"pointY":0.5}},"layers":[{"animations":[],"layers":[],"initialState":{"affineTransform":[1,0,0,1,0,0],"masksToBounds":false,"rotation":0,"scale":1,"position":{"pointX":240.5,"pointY":350.5},"width":484,"sublayerTransform":[1,0,0,0,0,1,0,0,0,0,1,0,0,0,0,1],"contentsRect":{"y":0,"x":0,"width":1,"height":1},"opacity":1,"edgeAntialiasingMask":0,"height":704,"hidden":false,"anchorPoint":{"pointX":0.5006886631989281,"pointY":0.5004734857515856}},"texture":"2F547A1FDD8A87CF921B459FBDFA3AB3"}]},{"animations":[],"initialState":{"affineTransform":[1,0,0,1,0,0],"masksToBounds":false,"rotation":0,"scale":1,"position":{"pointX":194.6666641235352,"pointY":597.3333129882812},"width":257,"sublayerTransform":[1,0,0,0,0,1,0,0,0,0,1,0,0,0,0,1],"contentsRect":{"y":0,"x":0,"width":1,"height":1},"opacity":1,"edgeAntialiasingMask":251658240,"height":164,"hidden":false,"anchorPoint":{"pointX":0.5,"pointY":0.5}},"layers":[{"animations":[],"layers":[],"initialState":{"affineTransform":[1,0,0,1,0,0],"masksToBounds":false,"rotation":0,"scale":1,"position":{"pointX":128.5,"pointY":82},"width":260,"sublayerTransform":[1,0,0,0,0,1,0,0,0,0,1,0,0,0,0,1],"contentsRect":{"y":0,"x":0,"width":1,"height":1},"opacity":1,"edgeAntialiasingMask":0,"height":167,"hidden":false,"anchorPoint":{"pointX":0.4987179389366737,"pointY":0.4990018741813249}},"texture":"80336EAB6D3062A19986B2D664A98CCB"}]},{"animations":[],"initialState":{"affineTransform":[1,0,0,1,0,0],"masksToBounds":false,"rotation":0,"scale":1,"position":{"pointX":597.3333358764648,"pointY":359.9999999999999},"width":1373,"sublayerTransform":[1,0,0,0,0,1,0,0,0,0,1,0,0,0,0,1],"contentsRect":{"y":0,"x":0,"width":1,"height":1},"opacity":1,"edgeAntialiasingMask":251658240,"height":720,"hidden":false,"anchorPoint":{"pointX":0.5,"pointY":0.5}},"layers":[{"animations":[],"layers":[],"initialState":{"affineTransform":[1,0,0,1,0,0],"masksToBounds":false,"rotation":0,"scale":1,"position":{"pointX":686.4999999999999,"pointY":360},"width":1377,"sublayerTransform":[1,0,0,0,0,1,0,0,0,0,1,0,0,0,0,1],"contentsRect":{"y":0,"x":0,"width":1,"height":1},"opacity":1,"edgeAntialiasingMask":0,"height":723,"hidden":true,"anchorPoint":{"pointX":0.5006051821906062,"pointY":0.5006915629322267}},"texture":"13FC1D004785409A6DD9A4F21AF9CCC1"}]},{"animations":[],"initialState":{"affineTransform":[1,0,0,1,0,0],"masksToBounds":false,"rotation":0,"scale":1,"position":{"pointX":703.3333435058594,"pointY":383.3333320617676},"width":793,"sublayerTransform":[1,0,0,0,0,1,0,0,0,0,1,0,0,0,0,1],"contentsRect":{"y":0,"x":0,"width":1,"height":1},"opacity":1,"edgeAntialiasingMask":251658240,"height":673,"hidden":false,"anchorPoint":{"pointX":0.5,"pointY":0.5}},"layers":[{"animations":[],"layers":[],"initialState":{"affineTransform":[1,0,0,1,0,0],"masksToBounds":false,"rotation":0,"scale":1,"position":{"pointX":396.5,"pointY":336.5},"width":797,"sublayerTransform":[1,0,0,0,0,1,0,0,0,0,1,0,0,0,0,1],"contentsRect":{"y":0,"x":0,"width":1,"height":1},"opacity":1,"edgeAntialiasingMask":0,"height":676,"hidden":true,"anchorPoint":{"pointX":0.5010456003837633,"pointY":0.5004930947659284}},"texture":"01B3871BA9FB8840BDC92BFC758C8D4E"}]},{"animations":[],"initialState":{"affineTransform":[1,0,0,1,0,0],"masksToBounds":false,"rotation":0,"scale":1,"position":{"pointX":414.6666564941406,"pointY":360},"width":1735,"sublayerTransform":[1,0,0,0,0,1,0,0,0,0,1,0,0,0,0,1],"contentsRect":{"y":0,"x":0,"width":1,"height":1},"opacity":1,"edgeAntialiasingMask":251658240,"height":720,"hidden":false,"anchorPoint":{"pointX":0.5,"pointY":0.5}},"layers":[{"animations":[],"layers":[],"initialState":{"affineTransform":[1,0,0,1,0,0],"masksToBounds":false,"rotation":0,"scale":1,"position":{"pointX":867.5,"pointY":360},"width":1738,"sublayerTransform":[1,0,0,0,0,1,0,0,0,0,1,0,0,0,0,1],"contentsRect":{"y":0,"x":0,"width":1,"height":1},"opacity":1,"edgeAntialiasingMask":0,"height":722,"hidden":true,"anchorPoint":{"pointX":0.4998082028159612,"pointY":0.5}},"texture":"9A26649A2F9F2AB8B9FE1A2628DE396B"}]},{"animations":[],"initialState":{"affineTransform":[1,0,0,1,0,0],"masksToBounds":false,"rotation":0,"scale":1,"position":{"pointX":233.3333320617676,"pointY":584},"width":355,"sublayerTransform":[1,0,0,0,0,1,0,0,0,0,1,0,0,0,0,1],"contentsRect":{"y":0,"x":0,"width":1,"height":1},"opacity":1,"edgeAntialiasingMask":251658240,"height":180,"hidden":false,"anchorPoint":{"pointX":0.5,"pointY":0.5}},"layers":[{"animations":[],"layers":[],"initialState":{"affineTransform":[1,0,0,1,0,0],"masksToBounds":false,"rotation":0,"scale":1,"position":{"pointX":177.5,"pointY":90},"width":358,"sublayerTransform":[1,0,0,0,0,1,0,0,0,0,1,0,0,0,0,1],"contentsRect":{"y":0,"x":0,"width":1,"height":1},"opacity":1,"edgeAntialiasingMask":0,"height":182,"hidden":true,"anchorPoint":{"pointX":0.5009310951446022,"pointY":0.5}},"texture":"08F2739282076EE2A5583663EA27282C"}]}]}}]}